[
    {
        "name":"Python",
        "detect":{
            "files":[
                {
                    "name":["*.py"],
                    "pattern":null,
                    "weight":0.5
                },
                {
                    "name":[],
                    "pattern":null,
                    "weight":0.5
                }
            ],
            "folders":[
                {
                    "name":"venv",
                    "files":[".Python"],
                    "weight":4
                }
            ]

        },
        "actions":{
            "before":[],
            "after":[],
            "exclude":{
                "files":[],
                "folders":["venv"],
                "dep_folder": null
            }
        }
    },
    {
        "name":"Javascript",
        "detect":{
            "files":[
                {
                    "name":["tslint.json", "eslint.json", "package.json", "tsconfig.json"],
                    "pattern":null,
                    "weight":4
                },
                {
                    "name":["*.js", "*.ts", "*.jsx"],
                    "pattern":null,
                    "weight":0.5
                }
            ],
            "folders":[
                {
                    "name":"node_modules",
                    "files":[],
                    "weight":2
                }
            ]

        },
        "actions":{
            "before":[],
            "after":[],
            "exclude":{
                "files":[],
                "folders":[],
                "dep_folder": "node_modules"
            }
        }
    },
    {
        "name":"Java",
        "detect":{
            "files":[
                {
                    "name":["*.class", "*.java", "*.jar"],
                    "pattern":null,
                    "weight":0.5
                },
                {
                    "name":["build.gradle"],
                    "pattern":null,
                    "weight":4
                }
            ],
            "folders":[
                {
                    "name":"gradle/wrapper",
                    "files":[],
                    "weight":4
                }
            ]
        },
        "actions":{
            "before":[],
            "after":[],
            "exclude":{
                "files":[],
                "folders":[],
                "dep_folder": null
            }
        }
    }
]